[{"date":"Wed, 04 Feb 2015 15:35:26 GMT","sloc":35,"lloc":14,"functions":5,"deliveredBugs":0.08918863237274595,"maintainability":81.37288052381368,"lintErrors":2,"difficulty":8.4},{"date":"Wed, 04 Feb 2015 15:35:54 GMT","sloc":35,"lloc":14,"functions":5,"deliveredBugs":0.08918863237274595,"maintainability":81.37288052381368,"lintErrors":2,"difficulty":8.4},{"date":"Wed, 04 Feb 2015 15:38:59 GMT","sloc":35,"lloc":14,"functions":5,"deliveredBugs":0.08918863237274595,"maintainability":81.37288052381368,"lintErrors":2,"difficulty":8.4},{"date":"Wed, 04 Feb 2015 18:13:55 GMT","sloc":37,"lloc":14,"functions":5,"deliveredBugs":0.08918863237274595,"maintainability":81.37288052381368,"lintErrors":2,"difficulty":8.4},{"date":"Wed, 04 Feb 2015 18:15:07 GMT","sloc":37,"lloc":14,"functions":5,"deliveredBugs":0.08918863237274595,"maintainability":81.37288052381368,"lintErrors":2,"difficulty":8.4}]